alex_sales/sales.py
alex_sales/settings.py
alex_sales-0.0.1.dist-info/METADATA
alex_sales-0.0.1.dist-info/WHEEL
alex_sales-0.0.1.dist-info/licenses/LICENSE.md
alex_sales-0.0.1.dist-info/RECORD
