Metadata-Version: 2.1
Name: alex_sales
Version: 0.0.1
Summary: My customized ORM on Sales
Project-URL: Homepage, https://github.com/AlejandroPqLz/sales_ibd_ORM.git
Project-URL: Bug Tracker, https://github.com/AlejandroPqLz/sales_ibd_ORM.git/issues
Author-email: "aleex.pl" <pq.lz.alejandro@gmail.com>
License: ## Licencia:
License-File: LICENSE.md
Classifier: License :: OSI Approved :: MIT License
Classifier: Operating System :: OS Independent
Classifier: Programming Language :: Python :: 3
Requires-Python: >=3.9
